README.md
setup.py
ccpayment/__init__.py
ccpayment/ccpayment.py
ccpayment/ccpayment_test.py
ccpayment/const.py
ccpayment/version.py
ccpayment.egg-info/PKG-INFO
ccpayment.egg-info/SOURCES.txt
ccpayment.egg-info/dependency_links.txt
ccpayment.egg-info/top_level.txt