Metadata-Version: 2.1
Name: ccpayment
Version: 1.0.2
Summary: ccpayment API
Home-page: https://github.com/cctip/ccpayment-sdk-python/ccpayment
Platform: all
Classifier: Programming Language :: Python :: 3.7
Classifier: Programming Language :: Python :: 3.8
Classifier: Programming Language :: Python :: 3.9
Classifier: Programming Language :: Python :: 3.10
